copilot_client/__init__.py
copilot_client/client.py
copilot_client-1.0.0.dist-info/METADATA
copilot_client-1.0.0.dist-info/WHEEL
copilot_client-1.0.0.dist-info/entry_points.txt
copilot_client-1.0.0.dist-info/top_level.txt
copilot_client-1.0.0.dist-info/RECORD
