Metadata-Version: 2.4
Name: copilot-client
Version: 1.0.0
Summary: Lightweight GitHub Copilot client with device login
Author-email: Alp Mete Senel <alpmete@senel.biz>
License: MIT
Project-URL: Homepage, https://github.com/AlpMeteSenel/copilot-python-client
Project-URL: Repository, https://github.com/AlpMeteSenel/copilot-python-client
Project-URL: Issues, https://github.com/AlpMeteSenel/copilot-python-client/issues
Keywords: github,copilot,client,chat,device-flow
Classifier: License :: OSI Approved :: MIT License
Classifier: Programming Language :: Python
Classifier: Programming Language :: Python :: 3
Classifier: Programming Language :: Python :: 3 :: Only
Classifier: Programming Language :: Python :: 3.10
Classifier: Programming Language :: Python :: 3.11
Classifier: Programming Language :: Python :: 3.12
Classifier: Programming Language :: Python :: 3.13
Classifier: Intended Audience :: Developers
Classifier: Topic :: Software Development :: Libraries
Classifier: Topic :: Software Development :: Libraries :: Python Modules
Requires-Python: >=3.10
Requires-Dist: httpx[http2]>=0.27
Provides-Extra: dev
Requires-Dist: pytest>=8; extra == "dev"
